{
  "Header": {
    "Type": "AnimatedTexture"
  },
  "Data": {
    "File": "rsrc/monster/SlimeBlue.png",
    "Objects": [
      {
        "Name": "SlimeBlueSouth",
        "Column": 1,
        "Row": 1,
        "Length": 3,
        "Ticks": 10,
        "Width": 12,
        "Height": 10
      },
      {
        "Name": "SlimeBlueWest",
        "Column": 1,
        "Row": 2,
        "Length": 3,
        "Ticks": 10,
        "Width": 12,
        "Height": 10
      },
      {
        "Name": "SlimeBlueEast",
        "Column": 1,
        "Row": 3,
        "Length": 3,
        "Ticks": 10,
        "Width": 12,
        "Height": 10
      },
      {
        "Name": "SlimeBlueNorth",
        "Column": 1,
        "Row": 4,
        "Length": 3,
        "Ticks": 10,
        "Width": 12,
        "Height": 10
      },
      {
        "Name": "SlimeBlueDead",
        "Column": 1,
        "Row": 5,
        "Length": 3,
        "Ticks": 10,
        "Width": 12,
        "Height": 10
      }
    ]
  }
}
